arcade_generator/__init__.py
arcade_generator/commands.py
arcade_generator/create_artifacts.py
arcade_generator/definitions.py
arcade_generator/errors.py
arcade_generator/main.py
arcade_generator/parsing.py
arcade_generator/utils.py
arcade_generator-0.12.0.dist-info/METADATA
arcade_generator-0.12.0.dist-info/WHEEL
arcade_generator-0.12.0.dist-info/entry_points.txt
arcade_generator-0.12.0.dist-info/licenses/LICENSE
arcade_generator-0.12.0.dist-info/RECORD
