Metadata-Version: 2.4
Name: arcade-generator
Version: 0.12.0
Summary: A static site generator
Author-email: Yabir Benchakhtir <yabirg@protonmail.com>
License: MIT
License-File: LICENSE
Classifier: Environment :: Console
Classifier: License :: OSI Approved :: MIT License
Classifier: Operating System :: OS Independent
Classifier: Programming Language :: Python :: 3
Classifier: Topic :: Internet :: WWW/HTTP
Requires-Python: >=3.12
Requires-Dist: click==8.3.1
Requires-Dist: jinja2==3.1.6
Requires-Dist: livereload==2.7.1
Requires-Dist: markdown==3.10
